{
  "Name": "All-Round Ambisonic decoder (AllRAD) and loudspeaker layout",
  "Description": "This configuration file was created with the IEM AllRADecoder v0.9.1 plug-in. 15 Sep 2021 2:11:50pm",
  "Decoder": {
    "Name": "Decoder",
    "Description": "A 3rd order Ambisonics decoder using the AllRAD approach.",
    "ExpectedInputNormalization": "n3d",
    "Weights": "maxrE",
    "WeightsAlreadyApplied": false,
    "Matrix": [
      [
        0.2330763339996338,
        -0.1903152912855148,
        1.271198584618105e-6,
        0.1903086155653,
        -0.112846165895462,
        -1.893223156912427e-6,
        -0.06515541672706604,
        -1.985698418138782e-6,
        -8.341253021626471e-8,
        -3.652257191788522e-6,
        -1.957697122634272e-6,
        1.490424438088667e-6,
        4.474345587368589e-6,
        1.590542410667695e-6,
        -1.323631124705571e-7,
        3.697178044603788e-6
      ],
      [
        0.2330860048532486,
        -0.1903082728385925,
        -3.844939328701003e-6,
        -0.1903152465820312,
        0.1128362193703651,
        2.71827570941241e-6,
        -0.06515065580606461,
        -2.747848157014232e-6,
        7.876167273934698e-8,
        1.864678552010446e-6,
        -1.251284800218855e-7,
        5.450775915960548e-6,
        -6.046093858458335e-6,
        -5.578369837166974e-6,
        8.727425182541992e-8,
        1.963827344297897e-6
      ],
      [
        0.2330763787031174,
        0.1903082728385925,
        1.266310619030264e-6,
        -0.1903150528669357,
        -0.1128463819622993,
        -1.901063342302223e-6,
        -0.06515540927648544,
        -1.987497398658888e-6,
        -8.207599222487261e-8,
        -3.650332246252219e-6,
        -1.957540462171892e-6,
        1.498151505074929e-6,
        4.471467491384828e-6,
        1.575007331666711e-6,
        -1.334745860503972e-7,
        3.699964054248994e-6
      ],
      [
        0.2330861389636993,
        0.1903154402971268,
        -3.846295385301346e-6,
        0.190308466553688,
        0.1128364652395248,
        2.720816610235488e-6,
        -0.06515070796012878,
        -2.748101223915e-6,
        7.956433023537102e-8,
        1.858087102846184e-6,
        -1.238526152746999e-7,
        5.454688562167576e-6,
        -6.041636879672296e-6,
        -5.572287591348868e-6,
        8.136368734312782e-8,
        1.966572881428874e-6
      ]
    ],
    "Routing": [
      13,
      15,
      17,
      19
    ]
  },
  "LoudspeakerLayout": {
    "Name": "A loudspeaker layout",
    "Loudspeakers": [
      {
        "Azimuth": -45.0,
        "Elevation": 0.0,
        "Radius": 1.0,
        "IsImaginary": false,
        "Channel": 13,
        "Gain": 1.0
      },
      {
        "Azimuth": -135.0,
        "Elevation": 0.0,
        "Radius": 1.0,
        "IsImaginary": false,
        "Channel": 15,
        "Gain": 1.0
      },
      {
        "Azimuth": 135.0,
        "Elevation": 0.0,
        "Radius": 1.0,
        "IsImaginary": false,
        "Channel": 17,
        "Gain": 1.0
      },
      {
        "Azimuth": 45.0,
        "Elevation": 0.0,
        "Radius": 1.0,
        "IsImaginary": false,
        "Channel": 19,
        "Gain": 1.0
      },
      {
        "Azimuth": 0.0,
        "Elevation": 90.0,
        "Radius": 1.0,
        "IsImaginary": true,
        "Channel": 20,
        "Gain": 0.0
      },
      {
        "Azimuth": 0.0,
        "Elevation": -90.0,
        "Radius": 1.0,
        "IsImaginary": true,
        "Channel": 21,
        "Gain": 0.0
      }
    ]
  }
}